zops.requirements_directory-0.1.0-py3.5-nspkg.pth
zops/requirements_directory/__init__.py
zops/requirements_directory/cli.py
zops.requirements_directory-0.1.0.dist-info/DESCRIPTION.rst
zops.requirements_directory-0.1.0.dist-info/METADATA
zops.requirements_directory-0.1.0.dist-info/RECORD
zops.requirements_directory-0.1.0.dist-info/WHEEL
zops.requirements_directory-0.1.0.dist-info/entry_points.txt
zops.requirements_directory-0.1.0.dist-info/metadata.json
zops.requirements_directory-0.1.0.dist-info/namespace_packages.txt
zops.requirements_directory-0.1.0.dist-info/top_level.txt
